github_release.py
githubrelease-1.5.9.dist-info/LICENSE_Apache_20
githubrelease-1.5.9.dist-info/METADATA
githubrelease-1.5.9.dist-info/WHEEL
githubrelease-1.5.9.dist-info/entry_points.txt
githubrelease-1.5.9.dist-info/top_level.txt
githubrelease-1.5.9.dist-info/version.txt
githubrelease-1.5.9.dist-info/version_full.txt
githubrelease-1.5.9.dist-info/RECORD
