Metadata-Version: 2.1
Name: githubrelease
Version: 1.5.9
Summary: githubrelease is a CLI to easily manage GitHub releases, assets and references
Home-page: https://github.com/j0057/github-release
Author: Joost Molenaar, Jean-Christophe Fillion-Robin
Author-email: j.j.molenaar@gmail.com, jchris.fillionr@kitware.com
License: Apache
Classifier: Environment :: Console
Classifier: Intended Audience :: Developers
Classifier: License :: OSI Approved :: Apache Software License
Classifier: Natural Language :: English
Classifier: Operating System :: OS Independent
Classifier: Programming Language :: Python :: 2
Classifier: Programming Language :: Python :: 3
Classifier: Topic :: Software Development :: Version Control
Classifier: Topic :: System :: Software Distribution
License-File: LICENSE_Apache_20
